.gitignore
CHANGES.txt
LICENSE.txt
MANIFEST.in
README.rst
requirements.txt
runtests.py
setup.cfg
setup.py
scielo_django_extensions.egg-info/PKG-INFO
scielo_django_extensions.egg-info/SOURCES.txt
scielo_django_extensions.egg-info/dependency_links.txt
scielo_django_extensions.egg-info/not-zip-safe
scielo_django_extensions.egg-info/top_level.txt
scielo_extensions/.DS_Store
scielo_extensions/__init__.py
scielo_extensions/__init__.pyc
scielo_extensions/context_processors.py
scielo_extensions/context_processors.pyc
scielo_extensions/fields.pyc
scielo_extensions/formfields.py
scielo_extensions/formfields.pyc
scielo_extensions/modelfields.py
scielo_extensions/modelfields.pyc
scielo_extensions/models.py
scielo_extensions/models.pyc
scielo_extensions/tools.py
scielo_extensions/tools.pyc
scielo_extensions/templatetags/.DS_Store
scielo_extensions/templatetags/__init__.py
scielo_extensions/templatetags/__init__.pyc
scielo_extensions/templatetags/scielo_common.py
scielo_extensions/templatetags/scielo_common.pyc
scielo_extensions/templatetags/scielo_ext.pyc
scielo_extensions/tests/__init__.py
scielo_extensions/tests/__init__.pyc
scielo_extensions/tests/tests_fields.py
scielo_extensions/tests/tests_fields.pyc
scielo_extensions/tests/tests_tools.py
scielo_extensions/tests/tests_tools.pyc