Metadata-Version: 1.0
Name: scielo-django-extensions
Version: 0.4
Summary: Extensions commonly used in SciELO for bibliographic metadata management.
Home-page: http://docs.scielo.org/
Author: SciELO
Author-email: scielo-dev@googlegroups.com
License: UNKNOWN
Keywords: SciELO Django Extensions
Platform: UNKNOWN
Classifier: Development Status :: 3 - Alpha
Classifier: Intended Audience :: Developers
Classifier: Programming Language :: Python
Classifier: Topic :: Internet :: WWW/HTTP
Classifier: Topic :: Internet :: WWW/HTTP :: WSGI
Classifier: Topic :: Internet :: WWW/HTTP :: WSGI :: Middleware
